symbrim/__init__.py
symbrim/bicycle/__init__.py
symbrim/bicycle/bicycle_base.py
symbrim/bicycle/cranks.py
symbrim/bicycle/front_frames.py
symbrim/bicycle/grounds.py
symbrim/bicycle/rear_frames.py
symbrim/bicycle/stationary_bicycle.py
symbrim/bicycle/tires.py
symbrim/bicycle/wheels.py
symbrim/bicycle/whipple_bicycle.py
symbrim/brim/__init__.py
symbrim/brim/base_connections.py
symbrim/brim/bicycle_rider.py
symbrim/brim/hand_grips.py
symbrim/brim/pedals.py
symbrim/brim/seats.py
symbrim/core/__init__.py
symbrim/core/attachment.py
symbrim/core/auxiliary.py
symbrim/core/base_classes.py
symbrim/core/mixins.py
symbrim/core/registry.py
symbrim/core/requirement.py
symbrim/core/singleton.py
symbrim/other/__init__.py
symbrim/other/rolling_disc.py
symbrim/rider/__init__.py
symbrim/rider/arms.py
symbrim/rider/base_connections.py
symbrim/rider/hip_joints.py
symbrim/rider/legs.py
symbrim/rider/pelvis.py
symbrim/rider/rider.py
symbrim/rider/rider_lean.py
symbrim/rider/sacrums.py
symbrim/rider/shoulder_joints.py
symbrim/rider/torso.py
symbrim/utilities/__init__.py
symbrim/utilities/benchmarking.py
symbrim/utilities/parametrize.py
symbrim/utilities/plotting.py
symbrim/utilities/testing.py
symbrim/utilities/utilities.py
symbrim-0.1.0.dist-info/LICENSE
symbrim-0.1.0.dist-info/METADATA
symbrim-0.1.0.dist-info/WHEEL
symbrim-0.1.0.dist-info/RECORD
