Metadata-Version: 2.1
Name: symbrim
Version: 0.1.0
Summary: A Modular and Extensible Open-Source Framework for Symbolic Creating Bicycle-Rider Models
Home-page: https://github.com/mechmotum/symbrim
License: CC0-1.0
Author: tjstienstra
Author-email: T.J.Stienstra@tudelft.nl
Requires-Python: >=3.9,<4.0
Classifier: License :: CC0 1.0 Universal (CC0 1.0) Public Domain Dedication
Classifier: Programming Language :: Python :: 3
Classifier: Programming Language :: Python :: 3.9
Classifier: Programming Language :: Python :: 3.10
Classifier: Programming Language :: Python :: 3.11
Classifier: Programming Language :: Python :: 3.12
Provides-Extra: parametrize
Provides-Extra: plotting
Requires-Dist: bicycleparameters (>=1.2.0,<2.0.0) ; extra == "parametrize"
Requires-Dist: importlib-metadata (>=8.5.0,<9.0.0) ; python_version < "3.8"
Requires-Dist: symmeplot (>=0.2.0,<0.3.0) ; extra == "plotting"
Requires-Dist: sympy (>=1.13,<2.0)
Requires-Dist: typing-extensions (>=4.12.2,<5.0.0)
Project-URL: Repository, https://github.com/mechmotum/symbrim
